reqinstall/__init__.py
reqinstall-1.1.0.dist-info/METADATA
reqinstall-1.1.0.dist-info/WHEEL
reqinstall-1.1.0.dist-info/top_level.txt
reqinstall-1.1.0.dist-info/RECORD
